commitPackage/__init__.py
commitPackage/__main__.py
commitPackage/lazyCommit.py
commitpackage-0.1.2.dist-info/licenses/LICENSE
commitpackage-0.1.2.dist-info/METADATA
commitpackage-0.1.2.dist-info/WHEEL
commitpackage-0.1.2.dist-info/entry_points.txt
commitpackage-0.1.2.dist-info/top_level.txt
commitpackage-0.1.2.dist-info/RECORD
