Metadata-Version: 2.4
Name: commitPackage
Version: 0.1.2
Summary: A fun and lighthearted package for generating random and styled Git commit messages.
Author-email: Sophia <sms10010@nyu.edu>
License:                     GNU GENERAL PUBLIC LICENSE
Project-URL: Homepage, https://github.com/software-students-spring2025/3-python-package-pack-it-up
Project-URL: Repository, https://github.com/software-students-spring2025/3-python-package-pack-it-up.git
Project-URL: Bug Tracker, https://github.com/software-students-spring2025/3-python-package-pack-it-up/issues
Keywords: git,commit,messages,automation,fun
Classifier: Programming Language :: Python :: 3
Classifier: Intended Audience :: Developers
Classifier: License :: OSI Approved :: MIT License
Classifier: Operating System :: OS Independent
Requires-Python: >=3.7
License-File: LICENSE
Provides-Extra: dev
Requires-Dist: pytest; extra == "dev"
Dynamic: license-file
